fomodoro/__init__.py
fomodoro/info.json
fomodoro/main.py
fomodoro/stopwatch.py
fomodoro/timer.py
fomodoro/utils.py
fomodoro-1.0.0.dist-info/METADATA
fomodoro-1.0.0.dist-info/WHEEL
fomodoro-1.0.0.dist-info/entry_points.txt
fomodoro-1.0.0.dist-info/top_level.txt
fomodoro-1.0.0.dist-info/RECORD
