Metadata-Version: 2.1
Name: fomodoro
Version: 1.0.0
Summary: Stopwatch and timer to work and study with Flowtime technique.
Author-email: LuisanaMTDev <luisanamartineztorres25@gmail.com>
Requires-Python: >=3.11
